{
    "GRider_problem_1_TVUe": "Get ready to answer your phone",
    "GRider_problem_1_QNCy": "Let’s get started!",
    "GRider_problem_1_khfQ": "Invalid phone number format",
    "GRider_problem_Error_in_TvoQ": "Invalid email format, please try again",
    "GRider_problem_1_OJfb": "To get details of your ride and allow you to see live updates from your driver.",
    "GRider_problem_1_jKLC": "Must contain at least two (2) of the following: numbers (123), letters (XYZ) or symbols (!@#)",
    "GRider_problem_1_qPmF": "Forgot password?",
    "GRider_problem_1_UYEe": "Invalid email format",
    "GRider_problem_1_ZDOA": "I have read and accept the terms and conditions and Privacy Policy",
    "GRider_problem_4_letters_iTxJ": "4 letters (not case-sensitive)",
    "GRider_problem_Privacy_VQfE": "Privacy",
    "GRider_problem_Privacy_Protocol_SEQl": "Your data is used so that you can receive personalised offers",
    "GRider_problem_1_ergm": "Personal Details",
    "GRider_problem_Enter_graphics_rHbZ": "Enter CAPTCHA Code",
    "GRider_problem_Tracking_RMvH": "Apple Advertising",
    "GRider_problem_8_16_hFRI": "8-16 characters",
    "GRider_problem_1_lxtR": "Enables you to see drivers nearby and locates your pickup point for an effortless pickup experience.",
    "GRider_problem_1_bWdN": "Allow",
    "GRider_problem_1_hMYy": "Enter Verification Code",
    "GRider_problem_1_TDdp": "Add Later",
    "GRider_problem_1_dDaW": "I don’t have a CURP",
    "GRider_problem_Graphic_verification_jpGm": "Unable to retrieve CAPTCHA. Please try again later",
    "GRider_problem_1_NWia": "Create Password",
    "GRider_problem_1_gLhu": "Enter Password",
    "GRider_problem_Network_error_WYIc": "Network error. Please try again later",
    "GRider_problem_Name_nPUO": "First Name",
    "GRider_problem_Verification_Code_aHwO": "Sign in with SMS Code",
    "GRider_problem_1_dxLe": "6-16 characters",
    "GRider_problem_1_SmMc": "I don't have a CPF",
    "GRider_problem_Click_on_CyFR": "Tap image to refresh",
    "GRider_problem_1_JlNJ": "Email",
    "GRider_problem_Exchange_Code_wcYA": "Promo Code (Optional)",
    "GRider_problem_1_HLGg": "Get Code via Phone Call",
    "GRider_problem_Name_ifGW": "Last Name",
    "GRider_point_Forget_the_zEVN": "Forgot Password",
    "GRider_point_Success_QqXB": "{frequency} attempts left today before account is temporarily locked",
    "GRider_point_You_have_Dxap": "Too many incorrect attempts, please try again tomorrow",
    "GRider_point_Operate_frequently_Nbpc": "Too many attempts. Please try again later",
    "GRider_point_SMS_sent_VVph": "Verification Code has been sent",
    "GRider_point_Try_again_Rofr": "Try Again",
    "GRider_point_Home_Gdqp": "Back to Homepage",
    "GRider_edition_To_be_QSpy": "I agree to all ",
    "GRider_edition_Im_not_qoQD": "Use Elsewhere",
    "GRider_edition_Name_bptQ": "First Name",
    "GRider_edition_Family_name_lnhs": "Last name",
    "GRider_edition_OK_bQOp": "OK",
    "GRider_edition_Common_countries_KeYi": "Frequently-Used Countries / Regions",
    "GRider_edition_Confirm_your_IpgC": "Add Your CPF",
    "GRider_edition__app_GRqt": "{app_name}",
    "GRider_edition_Your_name_GAKi": "Your Name",
    "GRider_edition_Get_verification_qyKD": "Get Code via WhatsApp",
    "GRider_edition_Please_check_uXnQ": "Check WhatsApp for Verification Code",
    "GRider_edition_Get_on_dDpU": "Pickup Point",
    "GRider_edition_Access_via_gbIq": "Get Code via Email",
    "GRider_edition_To_be_fRUW": "Kept secure. For ID verification only.",
    "GRider_edition_Not_allowed_MPLV": "Maybe Later",
    "GRider_edition_OK_CrBe": "Yes",
    "GRider_edition_Enter_password_TPaf": "Re-enter Password",
    "GRider_edition_Cancel_BQsb": "Cancel",
    "GRider_edition_Select_the_AwhP": "Select Country Code",
    "GRider_edition_No_verification_Cevy": "Didn't receive a code?",
    "GRider_edition_Verification_code_xFrF": "Code sent to {phone_number}",
    "GRider_edition_Cancel_Mbto": "Cancel",
    "GRider_edition_Your_email_AVPa": "Your Email Address",
    "GRider_edition_To_be_QtwN": "How'd you like to get your Verification Code?",
    "GRider_edition_To_be_AjEe": "Get Started",
    "GRider_edition_Terms_of_fdhJ": "Terms & Privacy Policy",
    "GRider_edition_To_be_mhlG": "You’ll receive the code via phone",
    "GRider_edition_Your_driver_BONv": "Your driver John has arrived at the pickup point. Look out for a white Toyota Camry",
    "GRider_edition_Agree_and_OntS": "Agree and Continue",
    "GRider_edition_Enter_your_YIig": "Enter mobile number",
    "GRider_edition_To_be_hxkW": "Enter your name",
    "GRider_edition_Next_step_HjtD": "Next",
    "GRider_edition_Bind_your_PCzn": "Add Your CURP",
    "GRider_edition_Resend_time_uqBU": "Resend {time_count}s",
    "GRider_edition_To_be_mmbE": "Verification Call",
    "GRider_edition_Enter_mobile_NKUY": "Your Mobile Number",
    "GRider_edition_CURP_Account_QdbQ": "Enter your CURP",
    "GRider_edition_Skip_vUcc": "Skip",
    "GRider_edition_Provision_of_zxkQ": "Your mobile number is registered in {location}. Are you sure you want to use DiDi in {location}?",
    "GRider_edition_To_be_mbBO": "Allows you to enjoy our app better. Don't worry, disabling this permission won't impact your app use",
    "GRider_edition_Resend_to_dubv": "Resend to {phone_number}"
}
